ps_environ/__init__.py
ps_environ/environ.py
ps_environ/tests.py
parameter_store_environ-0.1.2.dist-info/METADATA
parameter_store_environ-0.1.2.dist-info/WHEEL
parameter_store_environ-0.1.2.dist-info/top_level.txt
parameter_store_environ-0.1.2.dist-info/RECORD
