Metadata-Version: 2.1
Name: parameter-store-environ
Version: 0.1.2
Summary: A simple configuration variable wrapper around AWS SSM Parameter Store
Home-page: https://github.com/talroo/parameter-store-environ
Author: ebarajas
Author-email: ebarajas@talroo.com
License: MIT
Platform: UNKNOWN
Classifier: Programming Language :: Python :: 3 :: Only
Classifier: Programming Language :: Python :: 3.6
Classifier: License :: OSI Approved :: MIT License
Classifier: Operating System :: OS Independent
Requires-Python: >=3.6.0
Requires-Dist: boto3
